LICENSE
MANIFEST.in
README.rst
setup.cfg
setup.py
keiko/__init__.py
keiko/app.py
keiko/clients.py
keiko/flags.py
keiko.egg-info/PKG-INFO
keiko.egg-info/SOURCES.txt
keiko.egg-info/dependency_links.txt
keiko.egg-info/entry_points.txt
keiko.egg-info/not-zip-safe
keiko.egg-info/requires.txt
keiko.egg-info/top_level.txt
tests/__init__.py
tests/test_app.py
tests/test_clients.py
tests/test_flags.py