Metadata-Version: 1.1
Name: keiko
Version: 0.1.0
Summary: keiko is Python and Web API clients for Keiko-chan.
Home-page: https://github.com/lanius/keiko/
Author: lanius
Author-email: lanius@nirvake.org
License:    Copyright 2013 lanius
